firefalcon/__init__.py
firefalcon/_schemas.py
firefalcon/_utils.py
firefalcon/authentication.py
firefalcon/authorize.py
firefalcon/baseresource.py
firefalcon/firestore.py
firefalcon/onetomany.py
firefalcon-0.0.4.dist-info/METADATA
firefalcon-0.0.4.dist-info/WHEEL
firefalcon-0.0.4.dist-info/top_level.txt
firefalcon-0.0.4.dist-info/RECORD
